LICENSE
MANIFEST.in
README.rst
setup.py
CGITestConvert/__init__.py
CGITestConvert.egg-info/PKG-INFO
CGITestConvert.egg-info/SOURCES.txt
CGITestConvert.egg-info/dependency_links.txt
CGITestConvert.egg-info/entry_points.txt
CGITestConvert.egg-info/requires.txt
CGITestConvert.egg-info/top_level.txt