Metadata-Version: 1.1
Name: CGITestConvert
Version: 0.1
Summary: Converts CGITest Eclipse camera tracking files to Nuke .chan camera files
Home-page: http://github.com/shidarin/CGITestConvert
Author: Sean Wallitsch
Author-email: shidarin@alphamatte.com
License: MIT
Keywords: film tv
Platform: any
Classifier: Development Status :: 3 - Alpha
Classifier: Intended Audience :: End Users/Desktop
Classifier: Topic :: Multimedia :: Video
Classifier: Topic :: Software Development :: Libraries :: Python Modules
Classifier: License :: OSI Approved :: MIT License
Classifier: Programming Language :: Python :: 2
Classifier: Programming Language :: Python :: 2.6
Classifier: Programming Language :: Python :: 2.7
Classifier: Operating System :: OS Independent
Classifier: Natural Language :: English
